python_max_client/__init__.py
python_max_client/client.py
python_max_client/packet.py
python_max_client/functions/__init__.py
python_max_client/functions/channels.py
python_max_client/functions/chats.py
python_max_client/functions/groups.py
python_max_client/functions/messages.py
python_max_client/functions/profile.py
python_max_client/functions/users.py
python_max_client-1.0.1.dist-info/licenses/LICENSE
python_max_client-1.0.1.dist-info/METADATA
python_max_client-1.0.1.dist-info/WHEEL
python_max_client-1.0.1.dist-info/top_level.txt
python_max_client-1.0.1.dist-info/RECORD
