Metadata-Version: 2.4
Name: python-max-client
Version: 1.0.1
Summary: Python client for VK MAX messenger (OneMe)
Author-email: huxuxuya <huxuxuya@gmail.com>
License: MIT
Project-URL: Homepage, https://github.com/huxuxuya/python-max-client
Project-URL: Repository, https://github.com/huxuxuya/python-max-client
Project-URL: Issues, https://github.com/huxuxuya/python-max-client/issues
Keywords: vk,vkapi,max-messenger,vkmax,oneme,messenger,client
Classifier: Programming Language :: Python
Classifier: Programming Language :: Python :: 3
Classifier: Development Status :: 4 - Beta
Classifier: Intended Audience :: Developers
Classifier: Topic :: Communications :: Chat
Classifier: Topic :: Software Development :: Libraries :: Python Modules
Requires-Python: >=3.9
License-File: LICENSE
Requires-Dist: websockets>=12.0
Requires-Dist: httpx>=0.25.0
Dynamic: license-file
